{
  "10969": {
    "alive": false,
    "name": "Ricout",
    "surname": "Pryckert",
    "full name": "Ricout Pryckert",
    "born this way": {
      "sexuality label": "straight",
      "sexuality": 0.0,
      "romantic interest": 0.776,
      "sex interest": 0.706,
      "gender expression": 0.022,
      "sex": "m"
    },
    "age": 51,
    "birth year": 1154,
    "sex": "m",
    "faction": "Zealots",
    "income class": [
      1,
      "lower middle class"
    ],
    "personality": {
      "lawful-chaotic": 0.786,
      "nice-nasty": 0.253,
      "honest-false": 0.439,
      "dream": 0.366,
      "outgoing": 0.296
    },
    "homsoc": {
      "means": {
        "independent": true,
        "taken_care_of": false,
        "caretaker": false,
        "needs_care": false,
        "flags": []
      },
      "expression": {
        "sexuality expression": -0.001,
        "gender expression expression": 0.011
      }
    },
    "network": {
      "parents": "firstgen",
      "children": {
        "16577": {
          "key": 16577,
          "name": "Beatrice Pryckert",
          "age": 6,
          "alive": false,
          "sex": "f",
          "parents": {
            "mother": {
              "key": 10970,
              "name": "Hersewindis Mule",
              "age": 39,
              "alive": false,
              "sex": "f",
              "parents": "firstgen"
            },
            "father": {
              "key": 10969,
              "name": "Ricout Pryckert",
              "age": 51,
              "alive": false,
              "sex": "m",
              "parents": "firstgen"
            }
          }
        }
      },
      "relationship keys": {
        "spouse": [
          10971
        ],
        "child": {
          "birth": [
            16578
          ]
        },
        "unrelated": [
          18206
        ]
      }
    },
    "occupation": {
      "has job": true,
      "income class": [
        1,
        "lower middle class"
      ],
      "income": 0.968,
      "all_incomes": [
        0.963,
        0.988,
        0.902,
        1.012,
        1.069,
        0.968
      ],
      "job": {
        "lawful": true,
        "honest": true
      }
    },
    "genetics": {
      "skin_color": 8,
      "eye_color": "blue",
      "hair_color": "brown",
      "hair_color_code": 2,
      "hair_length": "medium",
      "beauty": 0.658,
      "hair_type": [
        "C",
        "C"
      ],
      "health": 0.438,
      "fertility": 0.601,
      "communication_impaired": false,
      "mobility_impaired": false,
      "cognitive_impaired": false,
      "disabilities": []
    },
    "memory": {
      "health": {
        "1200": {
          "health": {
            "change": false,
            "value_change": 0.0,
            "new_health": 0.635
          },
          "death": false
        },
        "1204": {
          "health": {
            "change": true,
            "value_change": -0.197,
            "new_health": 0.438
          },
          "death": true
        }
      },
      "homsoc": {
        "1200": {
          "independent": true,
          "needs_care": false,
          "taken_care_of": false,
          "caretaker": false
        }
      },
      "ocupation": {
        "1200": {
          "has job": true,
          "income": 0.988
        },
        "1201": {
          "has job": true,
          "income": 0.902
        },
        "1202": {
          "has job": true,
          "income": 1.012
        },
        "1203": {
          "has job": true,
          "income": 1.069
        },
        "1204": {
          "has job": true,
          "income": 0.968
        }
      },
      "events": {
        "1200": [
          {
            "topic": "birth",
            "year": 1154
          },
          {
            "topic": "job notice",
            "notice": "found job",
            "income": 0.963
          },
          {
            "topic": "new home",
            "home": {
              "income class": 1,
              "income class label": "lower middle class",
              "section": "stCoppelstraet.se1.c1",
              "street": "Coppelstraet",
              "neighborhood": "agnesbuurt",
              "unique id": 342
            }
          },
          {
            "topic": "new relationship",
            "key": 10971,
            "people": [
              10969,
              10970
            ],
            "people names": [
              "Ricout Pryckert",
              "Hersewindis Mule"
            ],
            "people ages": [
              46,
              38
            ],
            "label": "spouse",
            "committed": true
          },
          {
            "topic": "feelings change",
            "target": 10970,
            "target name": "Hersewindis Mule",
            "state": "solid love",
            "friendship label": "friend",
            "relationship": 10971
          }
        ],
        "1202": [
          {
            "topic": "job notice",
            "notice": "comfortable earnings",
            "income": 1.012
          },
          {
            "topic": "new relationship",
            "key": 16578,
            "people": [
              10969,
              16577
            ],
            "people names": [
              "Ricout Pryckert",
              "Beatrice Pryckert"
            ],
            "people ages": [
              49,
              0
            ],
            "label": "parentchild",
            "committed": false
          }
        ],
        "1203": [
          {
            "topic": "new relationship",
            "key": 18206,
            "people": [
              10969,
              12031
            ],
            "people names": [
              "Ricout Pryckert",
              "Alwin Crulleken"
            ],
            "people ages": [
              50,
              47
            ],
            "label": "unrelated",
            "committed": false
          }
        ],
        "1204": [
          {
            "topic": "death",
            "cause": "old age"
          }
        ]
      }
    },
    "key": 10969,
    "home": {
      "income class": 1,
      "income class label": "lower middle class",
      "section": "stCoppelstraet.se1.c1",
      "street": "Coppelstraet",
      "neighborhood": "agnesbuurt",
      "unique id": 342
    },
    "relationship status": {
      "taken": false,
      "married": true,
      "relationships": [
        10971
      ]
    },
    "friends": [
      10971,
      18206
    ],
    "enemies": []
  }
}