{
  "11650": {
    "alive": false,
    "name": "Ysaac",
    "surname": "Quic",
    "full name": "Ysaac Quic",
    "born this way": {
      "sexuality label": "straight",
      "sexuality": 0.062,
      "romantic interest": 0.762,
      "sex interest": 0.639,
      "gender expression": 0.073,
      "sex": "m"
    },
    "age": 54,
    "birth year": 1156,
    "sex": "m",
    "faction": "No religion",
    "income class": [
      2,
      "middle class"
    ],
    "personality": {
      "lawful-chaotic": 0.341,
      "nice-nasty": 0.0,
      "honest-false": 0.356,
      "dream": 0.82,
      "outgoing": 0.591
    },
    "attitude": {
      "dream": 0.82,
      "outgoing": 0.591
    },
    "homsoc": {
      "means": {
        "independent": true,
        "taken_care_of": false,
        "caretaker": false,
        "needs_care": false,
        "flags": []
      },
      "expression": {
        "sexuality expression": 0.031,
        "gender expression expression": 0.043
      }
    },
    "network": {
      "parents": "firstgen",
      "children": {
        "13267": {
          "key": 13267,
          "name": "Wein Quic",
          "age": 43,
          "alive": false,
          "sex": "m",
          "parents": {
            "mother": "Jute (11651)",
            "father": "Ysaac (11650)"
          }
        },
        "15377": {
          "key": 15377,
          "name": "Radulphus Quic",
          "age": 27,
          "alive": false,
          "sex": "m",
          "parents": {
            "mother": "Jute (11651)",
            "father": "Ysaac (11650)"
          }
        },
        "17202": {
          "key": 17202,
          "name": "Cesarius Quic",
          "age": 24,
          "alive": false,
          "sex": "m",
          "parents": {
            "mother": "Jute (11651)",
            "father": "Ysaac (11650)"
          }
        },
        "18644": {
          "key": 18644,
          "name": "Reynildis Quic",
          "age": 15,
          "alive": false,
          "sex": "f",
          "parents": {
            "mother": "Jute (11651)",
            "father": "Ysaac (11650)"
          }
        },
        "22043": {
          "key": 22043,
          "name": "Hersewindis Quic",
          "age": 11,
          "alive": false,
          "sex": "f",
          "parents": {
            "mother": "Jute (11651)",
            "father": "Ysaac (11650)"
          }
        },
        "24287": {
          "key": 24287,
          "name": "Lisebette Quic",
          "age": 44,
          "alive": true,
          "sex": "f",
          "parents": {
            "mother": "Jute (11651)",
            "father": "Ysaac (11650)"
          }
        }
      },
      "relationship keys": {
        "spouse": [
          11652
        ],
        "child": {
          "birth": [
            13268,
            15378,
            17203,
            18645,
            22044,
            24288
          ]
        }
      }
    },
    "occupation": {
      "has job": true,
      "income class": [
        2,
        "middle class"
      ],
      "income": 1.4249999999999998,
      "all_incomes": [
        0.801,
        1.2489999999999999,
        1.174,
        1.383,
        1.376,
        1.0399999999999998,
        0.984,
        1.42,
        1.524,
        1.524,
        1.4249999999999998
      ],
      "job": {
        "lawful": false,
        "honest": false
      }
    },
    "genetics": {
      "skin_color": 0,
      "eye_color": "green",
      "hair_color": "strawberry blonde",
      "hair_color_code": 5,
      "hair_type": [
        "S",
        "C"
      ],
      "health": 0.0,
      "fertility": 0.694,
      "communication_impaired": false,
      "mobility_impaired": false,
      "cognitive_impaired": false,
      "disabilities": []
    },
    "memory": {
      "health": {
        "1200": {
          "health": {
            "change": false,
            "value_change": 0.0,
            "new_health": 0.655
          },
          "death": false
        },
        "1206": {
          "health": {
            "change": true,
            "value_change": -0.238,
            "new_health": 0.417
          },
          "death": false
        },
        "1207": {
          "health": {
            "change": true,
            "value_change": -0.299,
            "new_health": 0.118
          },
          "death": false
        },
        "1208": {
          "health": {
            "change": true,
            "value_change": -0.049,
            "new_health": 0.069
          },
          "death": false
        },
        "1209": {
          "health": {
            "change": true,
            "value_change": -0.069,
            "new_health": 0.0
          },
          "death": true
        }
      },
      "events": {
        "1200": [
          {
            "topic": "birth",
            "year": 1156
          },
          {
            "topic": "job notice",
            "notice": "found job",
            "income": 0.801
          },
          {
            "topic": "job notice",
            "notice": "comfortable earnings",
            "income": 1.2489999999999999
          },
          {
            "topic": "new relationship",
            "key": 11652,
            "people": [
              11650,
              11651
            ],
            "people names": [
              "Ysaac Quic",
              "Jute Compere"
            ],
            "people ages": [
              44,
              19
            ],
            "label": "spouse",
            "committed": true
          },
          {
            "topic": "new relationship",
            "key": 13268,
            "people": [
              11650,
              13267
            ],
            "people names": [
              "Ysaac Quic",
              "Wein Quic"
            ],
            "people ages": [
              44,
              0
            ],
            "label": "parentchild",
            "committed": false
          }
        ],
        "1201": [
          {
            "topic": "new relationship",
            "key": 15378,
            "people": [
              11650,
              15377
            ],
            "people names": [
              "Ysaac Quic",
              "Radulphus Quic"
            ],
            "people ages": [
              46,
              0
            ],
            "label": "parentchild",
            "committed": false
          }
        ],
        "1202": [
          {
            "topic": "new relationship",
            "key": 17203,
            "people": [
              11650,
              17202
            ],
            "people names": [
              "Ysaac Quic",
              "Cesarius Quic"
            ],
            "people ages": [
              46,
              0
            ],
            "label": "parentchild",
            "committed": false
          }
        ],
        "1203": [
          {
            "topic": "new relationship",
            "key": 18645,
            "people": [
              11650,
              18644
            ],
            "people names": [
              "Ysaac Quic",
              "Reynildis Quic"
            ],
            "people ages": [
              47,
              0
            ],
            "label": "parentchild",
            "committed": false
          }
        ],
        "1204": [
          {
            "topic": "new relationship",
            "key": 22044,
            "people": [
              11650,
              22043
            ],
            "people names": [
              "Ysaac Quic",
              "Hersewindis Quic"
            ],
            "people ages": [
              48,
              0
            ],
            "label": "parentchild",
            "committed": false
          }
        ],
        "1205": [
          {
            "topic": "new relationship",
            "key": 24288,
            "people": [
              11650,
              24287
            ],
            "people names": [
              "Ysaac Quic",
              "Lisebette Quic"
            ],
            "people ages": [
              50,
              0
            ],
            "label": "parentchild",
            "committed": false
          },
          {
            "topic": "update",
            "update": "new friendship label",
            "relationship label": "parentchild",
            "friendship label": "friend",
            "relationship": 22044
          }
        ],
        "1206": [
          {
            "topic": "job notice",
            "notice": "comfortable earnings",
            "income": 1.42
          }
        ],
        "1209": [
          {
            "topic": "death",
            "cause": "sickness"
          }
        ]
      }
    },
    "key": 11650,
    "home": {
      "income class": 2,
      "income class label": "middle class",
      "section": "stBreestraat.se5.c2",
      "street": "Breestraat",
      "neighborhood": "olvbuurt",
      "unique id": 570
    },
    "relationship status": {
      "taken": true,
      "married": true,
      "relationships": [
        11652
      ]
    },
    "friends": [
      11652,
      22044
    ],
    "enemies": []
  }
}