{"11755": {"alive": false, "name": "Ysewin", "surname": "Bart", "full name": "Ysewin Bart", "born this way": {"sexuality label": "straight", "sexuality": 0.041, "romantic interest": 0.547, "sex interest": 0.929, "gender expression": 0.132, "sex": "m"}, "age": 52, "birth year": 1156, "sex": "m", "income class": [2, "middle class"], "personality": {"lawful-chaotic": 0.94, "nice-nasty": 0.3, "honest-false": 0.526}, "attitude": {"outgoing": 0.725, "dream": 0.104}, "homsoc": {"means": {"independent": true, "taken_care_of": false, "caretaker": false, "needs_care": false}, "expression": {"sexuality expression": 0.025, "gender expression expression": 0.055}}, "network": {"parents": "firstgen", "siblings": [], "children": {"birth": {}, "adopted": {}}, "relationships": {"11757": 11756}}, "occupation": {"has job": true, "income class": [2, "middle class"], "income": 0.997, "all_incomes": [0.955, 0.68, 0.676, 0.662, 1.126, 1.396, 1.054, 1.238, 0.997], "job": {"lawful": false, "honest": false}}, "genetics": {"skin_color": 1, "eye_color": "brown", "hair_color": "blonde", "hair_color_code": 4, "hair_type": ["C", "C"], "health": 0.298, "fertility": 0.83, "communication_impaired": false, "mobility_impaired": false, "cognitive_impaired": false, "disabilities": []}, "memory": {"health": {"1200": {"health": {"change": false, "value_change": 0.0, "new_health": 0.773}, "death": false}, "1206": {"health": {"change": true, "value_change": -0.213, "new_health": 0.56}, "death": false}, "1207": {"health": {"change": true, "value_change": -0.262, "new_health": 0.298}, "death": true}}, "events": {"1200": [{"topic": "new relationship", "key": 11757, "people": [11755, 11756], "people names": ["Ysewin Bart", "Liudburgis Coninc"], "label": "spouse", "committed": true}, {"topic": "new home", "home": {"income class": 2, "income class label": "middle class", "section": "stGoetscalcstraet.se3.c2", "street": "Goetscalcstraet", "neighborhood": "visbuurt", "unique id": 785}}, {"topic": "feelings change", "target": 11756, "target name": "Liudburgis Coninc", "state": "out of love", "relationship": 11757}]}}, "key": 11755, "home": {"income class": 2, "income class label": "middle class", "section": "stGoetscalcstraet.se3.c2", "street": "Goetscalcstraet", "neighborhood": "visbuurt", "unique id": 785}, "relationship status": {"taken": true, "married": true, "relationships": [11757]}}}