{"12131": {"alive": true, "name": "Nellen", "surname": "Buke", "full_name": "Nellen Buke", "born this way": {"sexuality label": "straight", "sexuality": 0.0, "romantic interest": 0.47, "sex interest": 0.683, "gender expression": 0.144, "sex": "f"}, "age": 47, "birth year": 1178, "sex": "f", "income class": [3, "upper middle class"], "personality": {"lawful-chaotic": 0.999, "nice-nasty": 0.619, "honest-false": 0.59}, "attitude": {"outgoing": 0.534, "dream": 0.435}, "homsoc": {"means": {"independent": true, "taken_care_of": true, "caretaker": true, "needs_care": false}, "expression": {"sexuality expression": -0.001, "gender expression expression": 0.05}}, "network": {"parents": "firstgen", "siblings": [], "children": {"birth": {"13173": {"key": 13173, "name": "Hersewindis van Bobone", "age": 18, "alive": false, "sex": "f", "parents": {"mother": "Nellen (12131)", "father": "Bobone (12130)"}}, "13824": {"key": 13824, "name": "Esa", "age": 16, "alive": true, "sex": "f", "parents": {"mother": "Nellen (12131)", "father": "Bobone (12130)"}}, "14307": {"key": 14307, "name": "Sara Bobonesdochter", "age": 13, "alive": true, "sex": "f", "parents": {"mother": "Nellen (12131)", "father": "Bobone (12130)"}}, "14481": {"key": 14481, "name": "Oderada", "age": 12, "alive": true, "sex": "f", "parents": {"mother": "Nellen (12131)", "father": "Bobone (12130)"}}}, "adopted": {}}, "relationships": {"12132": 12130}}, "occupation": {"lawful": null, "honest": null, "income class": [3, "upper middle class"], "hereditary": false}, "genetics": {"skin_color": 3, "eye_color": "green", "hair_color": "black", "hair_color_code": 0, "hair_type": ["S", "S"], "health": 0.74, "fertility": 0.781, "communication_impaired": false, "mobility impaired": false, "cognitive impaired": false, "disabilities": []}, "memory": {"health": {"1200": {"health": {"change": false, "value_change": 0.0, "new_health": 0.74}, "death": false}}, "events": {"1200": [{"topic": "new relationship", "key": 12132, "people": [12130, 12131]}], "1204": [{"topic": "new child", "child name": "Hersewindis", "child sex": "f", "child key": 13173, "kind": "birth"}], "1208": [{"topic": "new child", "child name": "Esa", "child sex": "f", "child key": 13824, "kind": "birth"}], "1211": [{"topic": "new child", "child name": "Sara", "child sex": "f", "child key": 14307, "kind": "birth"}], "1212": [{"topic": "new child", "child name": "Oderada", "child sex": "f", "child key": 14481, "kind": "birth"}]}}, "key": 12131, "home": {"income class": 3, "income class label": "upper middle class", "section": "stDen Hof.se5.c3", "street": "Den Hof", "neighborhood": "denhof", "key": "h946", "unique id": 947}}}