{
  "141735": {
    "alive": true,
    "name": "Hubrecht",
    "surname": "Vroede",
    "full name": "Hubrecht Vroede",
    "born this way": {
      "sexuality label": "gay",
      "sexuality": 0.937,
      "romantic interest": 0.703,
      "sex interest": 0.501,
      "gender expression": 0.738,
      "sex": "m"
    },
    "age": 7,
    "birth year": 1267,
    "sex": "m",
    "faction": "No religion",
    "income class": [
      1,
      "lower middle class"
    ],
    "personality": {
      "lawful-chaotic": 0.793,
      "nice-nasty": 0.719,
      "honest-false": 0.686,
      "dream": 0.196,
      "outgoing": 0.216
    },
    "homsoc": {
      "means": {
        "independent": false,
        "taken_care_of": false,
        "caretaker": true,
        "needs_care": true,
        "flags": [
          "neglected"
        ]
      },
      "expression": {
        "sexuality expression": 0.505,
        "gender expression expression": 0.302
      }
    },
    "network": {
      "parents": {
        "mother": {
          "key": 62666,
          "name": "Verthwi Vaken",
          "age": 37,
          "alive": true,
          "sex": "f",
          "parents": {
            "mother": {
              "key": 28501,
              "name": "Menoldis Dilanesdochter",
              "age": 28,
              "alive": false,
              "sex": "f",
              "parents": {
                "mother": {
                  "key": 11336,
                  "name": "Lutghardis Loeuin",
                  "age": 55,
                  "alive": false,
                  "sex": "f",
                  "parents": "firstgen"
                },
                "father": {
                  "key": 11335,
                  "name": "Dilane",
                  "age": 56,
                  "alive": false,
                  "sex": "m",
                  "parents": "firstgen"
                }
              }
            },
            "father": {
              "key": 24503,
              "name": "Eghenonis Vaken",
              "age": 56,
              "alive": false,
              "sex": "m",
              "parents": {
                "mother": {
                  "key": 11378,
                  "name": "Leanne",
                  "age": 49,
                  "alive": false,
                  "sex": "f",
                  "parents": "firstgen"
                },
                "father": {
                  "key": 11377,
                  "name": "Vastraid Vaken",
                  "age": 61,
                  "alive": false,
                  "sex": "m",
                  "parents": "firstgen"
                }
              }
            }
          }
        },
        "father": {
          "key": 57041,
          "name": "Gherbaren Vroede",
          "age": 40,
          "alive": true,
          "sex": "m",
          "parents": {
            "mother": {
              "key": 17471,
              "name": "Sara",
              "age": 54,
              "alive": false,
              "sex": "f",
              "parents": {
                "mother": {
                  "key": 10286,
                  "name": "Nimme",
                  "age": 36,
                  "alive": false,
                  "sex": "f",
                  "parents": "firstgen"
                },
                "father": {
                  "key": 10285,
                  "name": "Cees",
                  "age": 42,
                  "alive": false,
                  "sex": "m",
                  "parents": "firstgen"
                }
              }
            },
            "father": {
              "key": 14312,
              "name": "Dilane Vroede",
              "age": 53,
              "alive": false,
              "sex": "m",
              "parents": {
                "mother": {
                  "key": 10961,
                  "name": "Liudburgis",
                  "age": 36,
                  "alive": false,
                  "sex": "f",
                  "parents": "firstgen"
                },
                "father": {
                  "key": 10960,
                  "name": "Adam Vroede",
                  "age": 47,
                  "alive": false,
                  "sex": "m",
                  "parents": "firstgen"
                }
              }
            }
          }
        }
      },
      "children": {},
      "relationship keys": {
        "parent": [
          141736,
          141737
        ],
        "sibling": [
          141738,
          141739,
          141740,
          141741,
          149375,
          151558,
          154774
        ]
      }
    },
    "occupation": {
      "has job": false,
      "income class": [
        1,
        "lower middle class"
      ],
      "income": 0,
      "all_incomes": []
    },
    "genetics": {
      "skin_color": 6,
      "eye_color": "brown",
      "hair_color": "black",
      "hair_color_code": 0,
      "hair_length": "medium",
      "beauty": 0.787,
      "hair_type": [
        "C",
        "S"
      ],
      "health": 0.717,
      "fertility": 0.682,
      "communication_impaired": false,
      "mobility_impaired": false,
      "cognitive_impaired": false,
      "disabilities": []
    },
    "memory": {
      "health": {
        "1268": {
          "health": {
            "change": false,
            "value_change": 0.0,
            "new_health": 0.717
          },
          "death": false
        }
      },
      "homsoc": {
        "1268": {
          "independent": false,
          "needs_care": true,
          "taken_care_of": true,
          "caretaker": true
        },
        "1269": {
          "independent": false,
          "needs_care": true,
          "taken_care_of": false,
          "caretaker": true
        }
      },
      "ocupation": {
        "1268": {
          "has job": false,
          "income": 0
        },
        "1269": {
          "has job": false,
          "income": 0
        },
        "1270": {
          "has job": false,
          "income": 0
        },
        "1271": {
          "has job": false,
          "income": 0
        },
        "1272": {
          "has job": false,
          "income": 0
        },
        "1273": {
          "has job": false,
          "income": 0
        },
        "1274": {
          "has job": false,
          "income": 0
        }
      },
      "events": {
        "1267": [
          {
            "topic": "birth",
            "year": 1267
          },
          {
            "topic": "new home",
            "home": {
              "income class": 1,
              "income class label": "lower middle class",
              "section": "stHelle voet.se5.c1",
              "street": "Helle voet",
              "neighborhood": "jorisbuurt",
              "unique id": 103
            }
          },
          {
            "topic": "new relationship",
            "key": 141736,
            "people": [
              57041,
              141735
            ],
            "people names": [
              "Gherbaren Vroede",
              "Hubrecht Vroede"
            ],
            "people ages": [
              32,
              0
            ],
            "label": "parentchild",
            "committed": false
          },
          {
            "topic": "new relationship",
            "key": 141737,
            "people": [
              62666,
              141735
            ],
            "people names": [
              "Verthwi Vaken",
              "Hubrecht Vroede"
            ],
            "people ages": [
              30,
              0
            ],
            "label": "parentchild",
            "committed": false
          },
          {
            "topic": "new relationship",
            "key": 141738,
            "people": [
              116482,
              141735
            ],
            "people names": [
              "Amisius Vroede",
              "Hubrecht Vroede"
            ],
            "people ages": [
              7,
              0
            ],
            "label": "sibling",
            "committed": false
          },
          {
            "topic": "new relationship",
            "key": 141739,
            "people": [
              120336,
              141735
            ],
            "people names": [
              "Conzone Vroede",
              "Hubrecht Vroede"
            ],
            "people ages": [
              6,
              0
            ],
            "label": "sibling",
            "committed": false
          },
          {
            "topic": "new relationship",
            "key": 141740,
            "people": [
              126686,
              141735
            ],
            "people names": [
              "Godeweris Vroede",
              "Hubrecht Vroede"
            ],
            "people ages": [
              4,
              0
            ],
            "label": "sibling",
            "committed": false
          },
          {
            "topic": "new relationship",
            "key": 141741,
            "people": [
              129112,
              141735
            ],
            "people names": [
              "Conrad Vroede",
              "Hubrecht Vroede"
            ],
            "people ages": [
              4,
              0
            ],
            "label": "sibling",
            "committed": false
          },
          {
            "topic": "personality change",
            "change": true,
            "trait": "outgoing",
            "trigger": "neglect",
            "mod": -0.3
          }
        ],
        "1268": [
          {
            "topic": "event",
            "event": "plague",
            "year": 1268
          },
          {
            "topic": "update",
            "update": "new friendship label",
            "relationship label": "parentchild",
            "friendship label": "friend",
            "relationship": 141737
          },
          {
            "topic": "personality change",
            "change": true,
            "trait": "outgoing",
            "trigger": "neglect",
            "mod": -0.3
          },
          {
            "topic": "neglected"
          }
        ],
        "1269": [
          {
            "topic": "neglected"
          }
        ],
        "1270": [
          {
            "topic": "new relationship",
            "key": 149375,
            "people": [
              141735,
              149368
            ],
            "people names": [
              "Hubrecht Vroede",
              "Hako Vroede"
            ],
            "people ages": [
              3,
              0
            ],
            "label": "sibling",
            "committed": false
          },
          {
            "topic": "personality change",
            "change": true,
            "trait": "outgoing",
            "trigger": "neglect",
            "mod": -0.3
          },
          {
            "topic": "neglected"
          }
        ],
        "1271": [
          {
            "topic": "new relationship",
            "key": 151558,
            "people": [
              141735,
              151551
            ],
            "people names": [
              "Hubrecht Vroede",
              "Tetta Vroede"
            ],
            "people ages": [
              3,
              0
            ],
            "label": "sibling",
            "committed": false
          },
          {
            "topic": "neglected"
          }
        ],
        "1272": [
          {
            "topic": "new relationship",
            "key": 154774,
            "people": [
              141735,
              154767
            ],
            "people names": [
              "Hubrecht Vroede",
              "Laurens Vroede"
            ],
            "people ages": [
              4,
              0
            ],
            "label": "sibling",
            "committed": false
          }
        ],
        "1273": [
          {
            "topic": "update",
            "update": "new friendship label",
            "relationship label": "parentchild",
            "friendship label": "friend",
            "relationship": 141737
          }
        ],
        "1274": [
          {
            "topic": "update",
            "update": "new friendship label",
            "relationship label": "sibling",
            "friendship label": "friend",
            "relationship": 141740
          },
          {
            "topic": "neglected"
          }
        ]
      }
    },
    "key": 141735,
    "home": {
      "income class": 1,
      "income class label": "lower middle class",
      "section": "stHelle voet.se5.c1",
      "street": "Helle voet",
      "neighborhood": "jorisbuurt",
      "unique id": 103
    },
    "relationship status": {
      "taken": false,
      "married": false,
      "relationships": []
    },
    "friends": [
      141737,
      141738,
      141740,
      149375
    ],
    "enemies": []
  }
}