{
  "144491": {
    "alive": false,
    "name": "Breghtgherus",
    "surname": "Roden",
    "full name": "Breghtgherus Roden",
    "born this way": {
      "sexuality label": "gay",
      "sexuality": 0.955,
      "romantic interest": 0.828,
      "sex interest": 0.758,
      "gender expression": 0.436,
      "sex": "m"
    },
    "age": 2,
    "birth year": 1268,
    "sex": "m",
    "faction": "Dogmatists",
    "income class": [
      2,
      "middle class"
    ],
    "personality": {
      "lawful-chaotic": 0.321,
      "nice-nasty": 0.348,
      "honest-false": 0.189,
      "dream": 0.797,
      "outgoing": 0.321
    },
    "homsoc": {
      "means": {
        "independent": false,
        "taken_care_of": false,
        "caretaker": true,
        "needs_care": true,
        "flags": [
          "neglected"
        ]
      },
      "expression": {
        "sexuality expression": 0.513,
        "gender expression expression": 0.341
      }
    },
    "network": {
      "parents": {
        "mother": {
          "key": 34851,
          "name": "Moerseil van Macharius",
          "age": 48,
          "alive": false,
          "sex": "f",
          "parents": {
            "mother": {
              "key": 10550,
              "name": "Reymodis",
              "age": 57,
              "alive": false,
              "sex": "f",
              "parents": "firstgen"
            },
            "father": {
              "key": 10549,
              "name": "Macharius",
              "age": 53,
              "alive": false,
              "sex": "m",
              "parents": "firstgen"
            }
          }
        },
        "father": {
          "key": 35396,
          "name": "Denijs Roden",
          "age": 52,
          "alive": true,
          "sex": "m",
          "parents": {
            "mother": {
              "key": 12497,
              "name": "Saswe Blessard",
              "age": 57,
              "alive": false,
              "sex": "f",
              "parents": "firstgen"
            },
            "father": {
              "key": 12496,
              "name": "Ghisele Roden",
              "age": 45,
              "alive": false,
              "sex": "m",
              "parents": "firstgen"
            }
          }
        }
      },
      "children": {},
      "relationship keys": {
        "parent": [
          144492,
          144493
        ],
        "half-sibling": [
          145765,
          145766,
          145767,
          145768,
          145769,
          145770,
          145771,
          145781,
          145782,
          145783,
          145784
        ]
      }
    },
    "occupation": {
      "has job": false,
      "income class": [
        2,
        "middle class"
      ],
      "income": 0.025,
      "all_incomes": []
    },
    "genetics": {
      "skin_color": 3,
      "eye_color": "blue",
      "hair_color": "brown",
      "hair_color_code": 2,
      "hair_length": "medium",
      "beauty": 0.805,
      "hair_type": [
        "S",
        "S"
      ],
      "health": 0.807,
      "fertility": 0.885,
      "communication_impaired": false,
      "mobility_impaired": false,
      "cognitive_impaired": false,
      "disabilities": []
    },
    "memory": {
      "health": {
        "1269": {
          "health": {
            "change": false,
            "value_change": 0.0,
            "new_health": 0.807
          },
          "death": false
        },
        "1270": {
          "health": {
            "change": false,
            "value_change": 0.0,
            "new_health": 0.807
          },
          "death": true
        }
      },
      "homsoc": {
        "1269": {
          "independent": false,
          "needs_care": true,
          "taken_care_of": true,
          "caretaker": true
        },
        "1270": {
          "independent": false,
          "needs_care": true,
          "taken_care_of": false,
          "caretaker": true
        }
      },
      "ocupation": {
        "1269": {
          "has job": false,
          "income": 0.025
        },
        "1270": {
          "has job": false,
          "income": 0.025
        }
      },
      "events": {
        "1268": [
          {
            "topic": "birth",
            "year": 1268
          },
          {
            "topic": "new home",
            "home": {
              "income class": 2,
              "income class label": "middle class",
              "section": "stMarcktgang.se1.c2",
              "street": "Marcktgang",
              "neighborhood": "denhof",
              "unique id": 922
            }
          },
          {
            "topic": "new relationship",
            "key": 144492,
            "people": [
              35396,
              144491
            ],
            "people names": [
              "Denijs Roden",
              "Breghtgherus Roden"
            ],
            "people ages": [
              46,
              0
            ],
            "label": "parentchild",
            "committed": false
          },
          {
            "topic": "new relationship",
            "key": 144493,
            "people": [
              34851,
              144491
            ],
            "people names": [
              "Moerseil van Macharius",
              "Breghtgherus Roden"
            ],
            "people ages": [
              47,
              0
            ],
            "label": "parentchild",
            "committed": false
          },
          {
            "topic": "personality change",
            "change": true,
            "trait": "outgoing",
            "trigger": "neglect",
            "mod": -0.3
          },
          {
            "topic": "new relationship",
            "key": 145765,
            "people": [
              80234,
              144491
            ],
            "people names": [
              "Thedwi Cabelliau",
              "Breghtgherus Roden"
            ],
            "people ages": [
              20,
              0
            ],
            "label": "half-sibling",
            "committed": false
          },
          {
            "topic": "new relationship",
            "key": 145766,
            "people": [
              90024,
              144491
            ],
            "people names": [
              "Gheuardus Cabelliau",
              "Breghtgherus Roden"
            ],
            "people ages": [
              16,
              0
            ],
            "label": "half-sibling",
            "committed": false
          },
          {
            "topic": "new relationship",
            "key": 145767,
            "people": [
              93838,
              144491
            ],
            "people names": [
              "Brundonis Cabelliau",
              "Breghtgherus Roden"
            ],
            "people ages": [
              15,
              0
            ],
            "label": "half-sibling",
            "committed": false
          },
          {
            "topic": "new relationship",
            "key": 145768,
            "people": [
              100814,
              144491
            ],
            "people names": [
              "Myrthel Cabelliau",
              "Breghtgherus Roden"
            ],
            "people ages": [
              13,
              0
            ],
            "label": "half-sibling",
            "committed": false
          },
          {
            "topic": "new relationship",
            "key": 145769,
            "people": [
              108279,
              144491
            ],
            "people names": [
              "Remdo Cabelliau",
              "Breghtgherus Roden"
            ],
            "people ages": [
              11,
              0
            ],
            "label": "half-sibling",
            "committed": false
          },
          {
            "topic": "new relationship",
            "key": 145770,
            "people": [
              126954,
              144491
            ],
            "people names": [
              "Kerolus Hoghen",
              "Breghtgherus Roden"
            ],
            "people ages": [
              6,
              0
            ],
            "label": "half-sibling",
            "committed": false
          },
          {
            "topic": "new relationship",
            "key": 145771,
            "people": [
              140513,
              144491
            ],
            "people names": [
              "Piak",
              "Breghtgherus Roden"
            ],
            "people ages": [
              1,
              0
            ],
            "label": "half-sibling",
            "committed": false
          },
          {
            "topic": "new relationship",
            "key": 145781,
            "people": [
              97864,
              144491
            ],
            "people names": [
              "Lelien Roden",
              "Breghtgherus Roden"
            ],
            "people ages": [
              14,
              0
            ],
            "label": "half-sibling",
            "committed": false
          },
          {
            "topic": "new relationship",
            "key": 145782,
            "people": [
              101217,
              144491
            ],
            "people names": [
              "Oderada",
              "Breghtgherus Roden"
            ],
            "people ages": [
              13,
              0
            ],
            "label": "half-sibling",
            "committed": false
          },
          {
            "topic": "new relationship",
            "key": 145783,
            "people": [
              108608,
              144491
            ],
            "people names": [
              "Rolant Roden",
              "Breghtgherus Roden"
            ],
            "people ages": [
              11,
              0
            ],
            "label": "half-sibling",
            "committed": false
          },
          {
            "topic": "new relationship",
            "key": 145784,
            "people": [
              132783,
              144491
            ],
            "people names": [
              "Pieter",
              "Breghtgherus Roden"
            ],
            "people ages": [
              4,
              0
            ],
            "label": "half-sibling",
            "committed": false
          }
        ],
        "1269": [
          {
            "topic": "update",
            "update": "new friendship label",
            "relationship label": "half-sibling",
            "friendship label": "indifferent",
            "relationship": 145765
          },
          {
            "topic": "person died",
            "person": {
              "key": 34851,
              "name": "Moerseil van Macharius",
              "age": 48,
              "alive": false,
              "sex": "f",
              "parents": {
                "mother": {
                  "key": 10550,
                  "name": "Reymodis",
                  "age": 57,
                  "alive": false,
                  "sex": "f",
                  "parents": "firstgen"
                },
                "father": {
                  "key": 10549,
                  "name": "Macharius",
                  "age": 53,
                  "alive": false,
                  "sex": "m",
                  "parents": "firstgen"
                }
              }
            },
            "cause": "illness",
            "friendship label": "friend",
            "label": "parent"
          },
          {
            "topic": "person died",
            "person": {
              "key": 126954,
              "name": "Kerolus Hoghen",
              "age": 7,
              "alive": false,
              "sex": "m",
              "parents": {
                "mother": {
                  "key": 34851,
                  "name": "Moerseil van Macharius",
                  "age": 48,
                  "alive": false,
                  "sex": "f",
                  "parents": {
                    "mother": {
                      "key": 10550,
                      "name": "Reymodis",
                      "age": 57,
                      "alive": false,
                      "sex": "f",
                      "parents": "firstgen"
                    },
                    "father": {
                      "key": 10549,
                      "name": "Macharius",
                      "age": 53,
                      "alive": false,
                      "sex": "m",
                      "parents": "firstgen"
                    }
                  }
                },
                "father": {
                  "key": 18639,
                  "name": "Hughekine Hoghen",
                  "age": 58,
                  "alive": false,
                  "sex": "m",
                  "parents": {
                    "mother": {
                      "key": 11609,
                      "name": "Heilsota",
                      "age": 39,
                      "alive": false,
                      "sex": "f",
                      "parents": "firstgen"
                    },
                    "father": {
                      "key": 11608,
                      "name": "Walramus Hoghen",
                      "age": 46,
                      "alive": false,
                      "sex": "m",
                      "parents": "firstgen"
                    }
                  }
                }
              }
            },
            "cause": "childhood illness",
            "friendship label": "indifferent",
            "label": "half-sibling"
          },
          {
            "topic": "personality change",
            "change": true,
            "trait": "outgoing",
            "trigger": "neglect",
            "mod": -0.3
          },
          {
            "topic": "neglected"
          }
        ],
        "1270": [
          {
            "topic": "death",
            "cause": "childhood illness"
          }
        ]
      }
    },
    "key": 144491,
    "home": {
      "income class": 2,
      "income class label": "middle class",
      "section": "stMarcktgang.se1.c2",
      "street": "Marcktgang",
      "neighborhood": "denhof",
      "unique id": 922
    },
    "relationship status": {
      "taken": false,
      "married": false,
      "relationships": []
    },
    "friends": [
      144493,
      145766,
      145768,
      145771,
      145781
    ],
    "enemies": []
  }
}