{"17064": {"alive": true, "name": "Ghela", "surname": "Aec", "full_name": "Ghela Aec", "born this way": {"sexuality label": "straight", "sexuality": 0.0, "romantic interest": 0.625, "sex interest": 0.712, "gender expression": 0.171, "sex": "f"}, "age": 33, "birth year": 1266, "sex": "f", "income class": [2, "middle class"], "personality": {"lawful-chaotic": 0.0, "nice-nasty": 0.999, "honest-false": 0.457}, "attitude": {"outgoing": 0.312, "dream": 0.119}, "homsoc": {"means": {"independent": false, "taken_care_of": false, "caretaker": false, "needs_care": false}, "expression": {"sexuality expression": -0.001, "gender expression expression": 0.13}}, "network": {"parents": {"mother": "Heile (15099)", "father": "Wolcout (15026)"}, "siblings": [16574, 16647, 16786, 17679], "children": {"birth": {"18426": {"key": 18426, "name": "Hodine Croppes", "age": 14, "alive": true, "sex": "f", "parents": {"mother": "Ghela (17064)", "father": "Dybben (17062)"}}, "18931": {"key": 18931, "name": "Rase Croppes", "age": 6, "alive": true, "sex": "m", "parents": {"mother": "Ghela (17064)", "father": "Dybben (17062)"}}, "19140": {"key": 19140, "name": "Aghete Croppes", "age": 3, "alive": true, "sex": "f", "parents": {"mother": "Ghela (17064)", "father": "Dybben (17062)"}}}, "adopted": {}}, "relationships": {"18242": 17062}}, "occupation": {"has job": false, "income class": [2, "middle class"], "income": 0, "all_incomes": []}, "genetics": {"skin_color": 8, "eye_color": "brown", "hair_color": "black", "hair_color_code": 0, "hair_type": ["S", "S"], "health": 0.759, "fertility": 0.806, "communication_impaired": false, "mobility impaired": false, "cognitive impaired": false, "disabilities": []}, "memory": {"health": {"1267": {"health": {"change": false, "value_change": 0.0, "new_health": 0.759}, "death": false}}, "events": {"1275": [{"topic": "new sibling", "child name": "Breghlent", "child sex": "f", "child key": 17679, "kind": "birth"}], "1283": [{"topic": "new relationship", "key": 18242, "people": [17062, 17064], "label": "spouse", "committed": true}], "1284": [{"topic": "feelings change", "target": 17062, "state": "out of love", "relationship": 18242}], "1285": [{"topic": "sibling died", "person": {"key": 16786, "name": "Vreile Aec", "age": 23, "alive": false, "sex": "f", "parents": {"mother": "Heile (15099)", "father": "Wolcout (15026)"}}}, {"topic": "new child", "child name": "Hodine", "child sex": "f", "child key": 18426, "kind": "birth"}], "1293": [{"topic": "new child", "child name": "Rase", "child sex": "m", "child key": 18931, "kind": "birth"}], "1296": [{"topic": "person died", "person": {"key": 17062, "name": "Dybben Croppes", "age": 30, "alive": false, "sex": "m", "parents": {"mother": "Margareta (14992)", "father": "Lardies (14788)"}}}, {"topic": "new child", "child name": "Aghete", "child sex": "f", "child key": 19140, "kind": "birth"}], "1297": [{"key": 18242, "topic": "unmarried"}]}}, "key": 17064, "home": {"income class": 2, "income class label": "middle class", "section": "stBloemendaelse straet.se1.c2", "street": "Bloemendaelse straet", "neighborhood": "agnesbuurt", "unique id": 213}, "relationship status": {"taken": false, "married": false, "relationships": [18242]}}}